power5p_ocr_gpt/__init__.py
power5p_ocr_gpt-0.0.1.dist-info/METADATA
power5p_ocr_gpt-0.0.1.dist-info/WHEEL
power5p_ocr_gpt-0.0.1.dist-info/top_level.txt
power5p_ocr_gpt-0.0.1.dist-info/RECORD
