Metadata-Version: 2.1
Name: power5p-ocr-gpt
Version: 0.0.1
Summary: PYPI tutorial package by power5p
Home-page: UNKNOWN
Author: power5p
Author-email: jypower5p@gmail.com
License: UNKNOWN
Keywords: ocr,pypi
Platform: UNKNOWN
Classifier: Programming Language :: Python :: 3.8
Classifier: Programming Language :: Python :: 3.9
Requires-Python: >=3.8
Requires-Dist: scikit-learn
